<?xml version="1.0" encoding="UTF-8" standalone="yes"?>

<item>
<title>Az Tv</title>
<sportsdevil>http://www.hdtvler.tv/yayinlar/hdtv/embed.php?kanal=live_sd/aztv&telif=2</sportsdevil>
<thumbnail>https://www.ecanlitvizle.tv/logo/az-tv-izle-azerbaycan-tv-izle.png</thumbnail>
<referer>http://www.hdtvler.tv</referer>
</item>

<item>
<title>Ictimai Tv</title>
<sportsdevil>http://www.hdtvler.tv/yayinlar/hdtv/embed.php?kanal=live_sd/ictimaitv&telif=2</sportsdevil>
<thumbnail>https://www.ecanlitvizle.tv/logo/ictimai-tv-izle.png</thumbnail>
<referer>http://www.hdtvler.tv</referer>
</item>

<item>
<title>Medeniyyet TV</title>
<sportsdevil>http://www.hdtvler.tv/yayinlar/hdtv/embed.php?kanal=live_sd/medeniyettv&telif=2</sportsdevil>
<thumbnail>https://www.ecanlitvizle.tv/logo/medeniyet-az-tv.png</thumbnail>
<referer>http://www.hdtvler.tv</referer>
</item>

<item>
<title>Idman Tv</title>
<sportsdevil>http://www.hdtvler.tv/yayinlar/hdtv/embed.php?kanal=live_sd/idmantvhd&telif=2</sportsdevil>
<thumbnail>https://www.ecanlitvizle.tv/logo/idman-tv-izle.png</thumbnail>
<referer>http://www.hdtvler.tv</referer>
</item>

<item>
<title>CBC Spor</title>
<sportsdevil>http://www.hdtvler.tv/yayinlar/hdtv/embed.php?kanal=live_sd/cbcsport&telif=2</sportsdevil>
<thumbnail>https://www.ecanlitvizle.tv/logo/cbc-sport-az-tv.png</thumbnail>
<referer>http://www.hdtvler.tv</referer>
</item>

<item>
<title>CBC TV</title>
<sportsdevil>http://www.hdtvler.tv/yayinlar/hdtv/embed.php?kanal=live_sd/cbctv&telif=2</sportsdevil>
<thumbnail>https://www.ecanlitvizle.tv/logo/cbc-az-tv-cenub-tv.png</thumbnail>
<referer>http://www.hdtvler.tv</referer>
</item>

<item>
<title>ATV</title>
<sportsdevil>http://www.hdtvler.tv/yayinlar/hdtv/embed.php?kanal=live_sd/azadtv&telif=2</sportsdevil>
<thumbnail>https://www.ecanlitvizle.tv/logo/atv-azad-tv-izle.png</thumbnail>
<referer>http://www.hdtvler.tv</referer>
</item>

<item>
<title>Xezer Tv</title>
<sportsdevil>http://www.hdtvler.tv/yayinlar/hdtv/embed.php?kanal=live_sd/xazartv&telif=2</sportsdevil>
<thumbnail>https://www.ecanlitvizle.tv/logo/xezer-tv-izle.png</thumbnail>
<referer>http://www.hdtvler.tv</referer>
</item>

<item>
<title>Space Tv</title>
<sportsdevil>http://www.hdtvler.tv/yayinlar/hdtv/embed.php?kanal=live_sd/spacetv&telif=2</sportsdevil>
<thumbnail>https://www.ecanlitvizle.tv/logo/space-tv-az-izle.png</thumbnail>
<referer>http://www.hdtvler.tv</referer>
</item>

<item>
<title>Lider Tv</title>
<sportsdevil>http://www.hdtvler.tv/yayinlar/hdtv/embed.php?kanal=live_sd/lidertv&telif=2</sportsdevil>
<thumbnail>https://www.ecanlitvizle.tv/logo/lider-tv-az-izle.png</thumbnail>
<referer>http://www.hdtvler.tv</referer>
</item>

<item>
<title>ARB</title>
<sportsdevil>http://www.hdtvler.tv/yayinlar/azeri/regionaltv.php</sportsdevil>
<thumbnail>https://image.ibb.co/hji8Kw/Webp_net_resizeimage.png</thumbnail>
<referer>http://www.hdtvler.tv</referer>
</item>

<item>
<title>TMB Tv</title>
<sportsdevil>http://www.hdtvler.tv/yayinlar/hdtv/embed.php?kanal=live_sd/tmbtv&telif=2</sportsdevil>
<thumbnail>https://www.ecanlitvizle.tv/logo/tmb-tv-izle.png</thumbnail>
<referer>http://www.hdtvler.tv</referer>
</item>

<item>
<title>Muz Tv</title>
<sportsdevil>http://www.hdtvler.tv/yayinlar/hdtv/embed.php?kanal=live_sd/muztvaz&telif=2</sportsdevil>
<thumbnail>https://www.ecanlitvizle.tv/logo/muz-tv-az.png</thumbnail>
<referer>http://www.hdtvler.tv</referer>
</item>

<item>
<title>Can Azerbaycan</title>
<sportsdevil>http://www.hdtvler.tv/yayinlar/canazerbaycan-live.php</sportsdevil>
<thumbnail>https://image.ibb.co/eqt3mb/Webp_net_resizeimage.png</thumbnail>
<referer>http://www.hdtvler.tv</referer>
</item>

<item>
<title>Kanal S</title>
<sportsdevil>http://www.hdtvler.tv/yayinlar/azeri/kanals.php</sportsdevil>
<thumbnail>https://image.ibb.co/fx6vzw/Webp_net_resizeimage_1.png</thumbnail>
<referer>http://www.hdtvler.tv</referer>
</item>

<item>
<title>Inter Az </title>
<sportsdevil>http://www.hdtvler.tv/yayinlar/hdtv/embed.php?kanal=live_sd/interaztv&telif=2</sportsdevil>
<thumbnail>https://www.ecanlitvizle.tv/logo/inter-az.png</thumbnail>
<referer>http://www.hdtvler.tv</referer>
</item>

<item>
<title>Gunaz TV</title>
<sportsdevil>http://www.hdtvler.tv/yayinlar/azeri/gunaztv-az.php</sportsdevil>
<thumbnail>https://image.ibb.co/hhWymb/Webp_net_resizeimage_2.png</thumbnail>
<referer>http://www.hdtvler.tv</referer>
</item>

<item>
<title>Dunya TV</title>
<sportsdevil>http://www.hdtvler.tv/yayinlar/hdtv/embed.php?kanal=live_sd/dunyatv&telif=2</sportsdevil>
<thumbnail>https://www.ecanlitvizle.tv/logo/dunya-tv-az.png</thumbnail>
<referer>http://www.hdtvler.tv</referer>
</item>

<item>
<title>Dalga TV</title>
<sportsdevil>http://www.hdtvler.tv/yayinlar/azeri/dalgatvaz.php</sportsdevil>
<thumbnail>https://image.ibb.co/h6dxCG/timthumb_2.png</thumbnail>
<referer>http://www.hdtvler.tv</referer>
</item>

<item>
<title>AzStar TV</title>
<sportsdevil>http://www.hdtvler.tv/yayinlar/hdtv/embed.php?kanal=live_sd/azstartv&telif=2</sportsdevil>
<thumbnail>https://www.ecanlitvizle.tv/logo/az-star-tv.png</thumbnail>
<referer>http://www.hdtvler.tv</referer>
</item>
